posixath/__about__.py
posixath/__init__.py
posixath/__main__.py
posixath/pytest.ini
posixath/tests/__init__.py
posixath/tests/conftest.py
posixath/tests/linux/__init__.py
posixath/tests/linux/test_T1018.py
posixath/tests/linux/test_T1055_008.py
posixath/tests/linux/test_T1548_001.py
posixath/tests/linux/library/T1548_001/Makefile
posixath/tests/linux/library/T1548_001/setgid.c
posixath/tests/linux/library/T1548_001/setuid.c
posixath/tests/macos/__init__.py
posixath/tests/macos/test_T1059_002.py
posixath/tests/macos/test_T1059_007.py
posixath/tests/macos/test_T1620.py
posixath/tests/macos/library/T1059_002/nsapplescript_example.swift
posixath/tests/macos/library/T1059_002/whoami.scpt
posixath/tests/macos/library/T1059_002/whoami.sh
posixath/tests/macos/library/T1059_007/osakit_example.swift
posixath/tests/macos/library/T1059_007/whoami_jxa.scpt
posixath/tests/macos/library/T1059_007/whoami_jxa.sh
posixath/tests/macos/library/T1620/hello.c
posixath/tests/macos/library/T1620/nscreateobjectfileimagefrommemory.c
posixath/utils/__init__.py
posixath/utils/common.py
posixath/utils/hexdump.py
posixath/utils/ptrace.py
posixath/utils/tests/__init__.py
posixath/utils/tests/test_common.py
posixath-0.0.5.dist-info/METADATA
posixath-0.0.5.dist-info/WHEEL
posixath-0.0.5.dist-info/RECORD
