Metadata-Version: 2.1
Name: posixath
Version: 0.0.5
Summary: A suite of tools for simulating MITRE ATT&CK techniques for Linux and macOS
Project-URL: Documentation, https://github.com/redcanaryco/AtomicTestHarnesses/wiki/Getting-started-on-MacOS-and-Linux
Project-URL: Issues, https://github.com/redcanaryco/AtomicTestHarnesses/issues
Project-URL: Source, https://github.com/redcanaryco/AtomicTestHarnesses/tree/master/posix
Author-email: Redcanary <research@redcanary.com>
License-Expression: BSD-3-Clause
Keywords: ATT&CK,MITRE,atomic,posix
Classifier: Development Status :: 4 - Beta
Classifier: Programming Language :: Python
Classifier: Programming Language :: Python :: 3.10
Classifier: Programming Language :: Python :: 3.11
Classifier: Programming Language :: Python :: Implementation :: CPython
Classifier: Programming Language :: Python :: Implementation :: PyPy
Requires-Python: >=3.10
Requires-Dist: psutil
Requires-Dist: pytest
Requires-Dist: rich
